auto_whatsapp/__init__.py
auto_whatsapp/auto_whatsapp.py
auto_whatsapp-0.0.5.dist-info/LICENSE
auto_whatsapp-0.0.5.dist-info/METADATA
auto_whatsapp-0.0.5.dist-info/WHEEL
auto_whatsapp-0.0.5.dist-info/top_level.txt
auto_whatsapp-0.0.5.dist-info/RECORD
