Metadata-Version: 2.1
Name: auto-whatsapp
Version: 0.0.5
Summary: Automating WhatsApp using python with custom multiple messaging options, attachment options and supporting images and video sending
Home-page: https://github.com/adil-01/auto-whatsapp
Author: Adil
Author-email: adilbacker11@gmail.com
License: UNKNOWN
Project-URL: Bug Tracker, https://github.com/adil-01/auto-whatsapp/issues
Keywords: automate,whatsapp,py-whatsapp,web_whatsapp,python_whatsapp
Platform: UNKNOWN
Classifier: Programming Language :: Python :: 3
Classifier: License :: OSI Approved :: MIT License
Classifier: Operating System :: OS Independent
Requires-Python: >=3.6
License-File: LICENSE
